rag2f/__init__.py
rag2f/_version.py
rag2f/core/__init__.py
rag2f/core/rag2f.py
rag2f/core/utils.py
rag2f/core/dto/__init__.py
rag2f/core/dto/indiana_jones_dto.py
rag2f/core/dto/johnny5_dto.py
rag2f/core/dto/result_dto.py
rag2f/core/dto/xfiles_dto.py
rag2f/core/indiana_jones/__init__.py
rag2f/core/indiana_jones/exceptions.py
rag2f/core/indiana_jones/indiana_jones.py
rag2f/core/johnny5/__init__.py
rag2f/core/johnny5/exceptions.py
rag2f/core/johnny5/johnny5.py
rag2f/core/morpheus/__init__.py
rag2f/core/morpheus/morpheus.py
rag2f/core/morpheus/package_installer.py
rag2f/core/morpheus/plugin.py
rag2f/core/morpheus/plugin_manifest.py
rag2f/core/morpheus/decorators/__init__.py
rag2f/core/morpheus/decorators/hook.py
rag2f/core/morpheus/decorators/plugin_decorator.py
rag2f/core/optimus_prime/__init__.py
rag2f/core/optimus_prime/optimus_prime.py
rag2f/core/protocols/__init__.py
rag2f/core/protocols/embedder.py
rag2f/core/spock/__init__.py
rag2f/core/spock/spock.py
rag2f/core/xfiles/__init__.py
rag2f/core/xfiles/capabilities.py
rag2f/core/xfiles/exceptions.py
rag2f/core/xfiles/repository.py
rag2f/core/xfiles/types.py
rag2f/core/xfiles/validation.py
rag2f/core/xfiles/xfiles.py
rag2f-0.1.2.dist-info/licenses/LICENSE
rag2f-0.1.2.dist-info/METADATA
rag2f-0.1.2.dist-info/WHEEL
rag2f-0.1.2.dist-info/top_level.txt
rag2f-0.1.2.dist-info/RECORD
