Metadata-Version: 2.4
Name: rag2f
Version: 0.1.2
Summary: RAG2F - Retrieval Augmented Generation Framework
Author-email: Dario Chini <dariochini@gmail.com>
License: GPL-3.0
Project-URL: Repository, https://github.com/rag2f/rag2f
Classifier: Development Status :: 3 - Alpha
Classifier: Intended Audience :: Developers
Classifier: License :: OSI Approved :: GNU General Public License v3 (GPLv3)
Classifier: Programming Language :: Python :: 3.12
Requires-Python: >=3.12
License-File: LICENSE
Requires-Dist: inflection
Requires-Dist: python-dotenv
Requires-Dist: pydantic
Requires-Dist: packaging
Provides-Extra: dev
Requires-Dist: pre-commit==4.5.1; extra == "dev"
Requires-Dist: ruff==0.14.11; extra == "dev"
Requires-Dist: pytest; extra == "dev"
Requires-Dist: pytest-asyncio; extra == "dev"
Requires-Dist: rich; extra == "dev"
Requires-Dist: pytest-rich; extra == "dev"
Requires-Dist: pytest-icdiff; extra == "dev"
Requires-Dist: pytest-clarity; extra == "dev"
Requires-Dist: pytest-instafail; extra == "dev"
Requires-Dist: coverage; extra == "dev"
Requires-Dist: pytest-cov; extra == "dev"
Requires-Dist: respx; extra == "dev"
Provides-Extra: rag2f-openai-embedder
Requires-Dist: rag2f-openai-embedder>=0.1.0.dev5; extra == "rag2f-openai-embedder"
Dynamic: license-file
